dh2vrml/__init__.py
dh2vrml/cli.py
dh2vrml/dhparams.py
dh2vrml/exporter.py
dh2vrml/mdl_template.py
dh2vrml/util.py
dh2vrml-0.1.12.dist-info/entry_points.txt
dh2vrml-0.1.12.dist-info/LICENSE
dh2vrml-0.1.12.dist-info/WHEEL
dh2vrml-0.1.12.dist-info/METADATA
dh2vrml-0.1.12.dist-info/RECORD
