Metadata-Version: 2.1
Name: dh2vrml
Version: 0.1.12
Summary: Library and CLI tool to convert Denavit-Hartenberg parameters to an X3D model
Home-page: https://github.com/Gigahawk/dh2vrml
License: MIT
Author: Jasper Chan
Author-email: jasperchan515@gmail.com
Requires-Python: >=3.8,<3.11
Classifier: License :: OSI Approved :: MIT License
Classifier: Programming Language :: Python :: 3
Classifier: Programming Language :: Python :: 3.10
Classifier: Programming Language :: Python :: 3.8
Classifier: Programming Language :: Python :: 3.9
Requires-Dist: PyYAML (>=6.0,<7.0)
Requires-Dist: click (>=8.0.3,<9.0.0)
Requires-Dist: numpy (>=1.21,<2.0)
Requires-Dist: pandas (>=1.3,<2.0)
Requires-Dist: scipy (>=1.7.0,<2.0.0)
Requires-Dist: toml (>=0.10.2,<0.11.0)
Requires-Dist: x3d (>=4.0.47,<5.0.0)
Requires-Dist: xmlschema (>=1.9.2,<2.0.0)
Project-URL: Repository, https://github.com/Gigahawk/dh2vrml
